verify_import/__init__.py
verify_import/__init__.pyi
verify_import/cli.py
verify_import/main.py
verify_import-0.1.4.dist-info/METADATA
verify_import-0.1.4.dist-info/WHEEL
verify_import-0.1.4.dist-info/entry_points.txt
verify_import-0.1.4.dist-info/top_level.txt
verify_import-0.1.4.dist-info/RECORD
