Metadata-Version: 2.1
Name: verify-import
Version: 0.1.4
Summary: Simple tool to verify all submodules import without error
Author-email: Marcel Claramunt <marcel@moveread.com>
Project-URL: repo, https://github.com/marciclabas/codegen.git
Requires-Python: >=3.10
Requires-Dist: lazy-loader
Requires-Dist: dslog[rich]
